fabrics/.gitignore
fabrics/__init__.py
fabrics/components/energies/execution_energies.py
fabrics/components/environment/__init__.py
fabrics/components/leaves/attractor.py
fabrics/components/leaves/dynamic_attractor.py
fabrics/components/leaves/dynamic_geometry.py
fabrics/components/leaves/dynamic_leaf.py
fabrics/components/leaves/geometry.py
fabrics/components/leaves/leaf.py
fabrics/components/maps/parameterized_maps.py
fabrics/components/robot_representation/__init__.py
fabrics/defaults/default_energies.py
fabrics/defaults/default_geometries.py
fabrics/defaults/default_leaves.py
fabrics/defaults/default_maps.py
fabrics/diffGeometry/casadi_helpers.py
fabrics/diffGeometry/diffMap.py
fabrics/diffGeometry/energized_geometry.py
fabrics/diffGeometry/energy.py
fabrics/diffGeometry/geometry.py
fabrics/diffGeometry/spec.py
fabrics/diffGeometry/speedControl.py
fabrics/helpers/casadiFunctionWrapper.py
fabrics/helpers/constants.py
fabrics/helpers/distances.py
fabrics/helpers/exceptions.py
fabrics/helpers/functions.py
fabrics/helpers/geometric_primitives.py
fabrics/helpers/variables.py
fabrics/planner/configuration_classes.py
fabrics/planner/non_holonomic_parameterized_planner.py
fabrics/planner/parameterized_planner.py
fabrics/planner/serialized_planner.py
fabrics-0.10.0.dist-info/LICENSE
fabrics-0.10.0.dist-info/METADATA
fabrics-0.10.0.dist-info/WHEEL
fabrics-0.10.0.dist-info/RECORD
