Metadata-Version: 2.1
Name: fabrics
Version: 0.10.0
Summary: Optimization fabrics in python.
Home-page: https://tud-amr/fabrics
License: GPL-3.0-or-later
Keywords: robotics,motion-planning,geometry
Author: Max Spahn
Author-email: m.spahn@tudelft.nl
Requires-Python: >=3.10,<4.0
Classifier: License :: OSI Approved :: GNU General Public License v3 or later (GPLv3+)
Classifier: Programming Language :: Python :: 3
Classifier: Programming Language :: Python :: 3.10
Classifier: Programming Language :: Python :: 3.11
Classifier: Programming Language :: Python :: 3.12
Classifier: Programming Language :: Python :: 3.13
Requires-Dist: casadi (>=3.5.5)
Requires-Dist: deprecation (>=2.1.0,<3.0.0)
Requires-Dist: forwardkinematics (>=1.2.2,<2.0.0)
Requires-Dist: geomdl (>=5.3.1,<6.0.0)
Requires-Dist: mpscenes (>=0.4,<0.5)
Requires-Dist: numpy (>=1.15.3,<2.0.0)
Requires-Dist: pickle-mixin (>=1.0.2,<2.0.0)
Requires-Dist: pynput (>=1.7.6,<2.0.0)
Requires-Dist: pyquaternion (>=0.9.9,<0.10.0)
Requires-Dist: pytest (==6.2.5)
Requires-Dist: quaternionic (>=1.0.0,<2.0.0)
Requires-Dist: vector (>=1.1.1,<2.0.0)
Project-URL: Repository, https://tud-amr/fabrics
